[{"date":"2024-07-01","title":"M.Sc. Physics II Semester-2079 Exam Result","link":"https://iost.tu.edu.np/notices/3595"},{"date":"2024-06-30","title":"B.Sc.CSIT IV Semester-2078 Exam Result","link":"https://iost.tu.edu.np/notices/3577"},{"date":"2024-06-30","title":"M.Sc. CSIT II Semester-2079 Exam Result","link":"https://iost.tu.edu.np/notices/3576"},{"date":"2024-06-30","title":"B.Sc. CSIT V Semester-2078 Form Fill Up Notice","link":"https://iost.tu.edu.np/notices/3575"},{"date":"2024-06-30","title":"M.Sc. III Semester-2079 Form Fill Up Notice","link":"https://iost.tu.edu.np/notices/3574"},{"date":"2024-06-30","title":"Bachelor in Information Technology (BIT) V Semester-2078 Form Fill Up Notice","link":"https://iost.tu.edu.np/notices/3573"}]